sqlalchemy_oso_cloud/__init__.py
sqlalchemy_oso_cloud/auth.py
sqlalchemy_oso_cloud/orm.py
sqlalchemy_oso_cloud/oso.py
sqlalchemy_oso_cloud/py.typed
sqlalchemy_oso_cloud/query.py
sqlalchemy_oso_cloud/select_impl.py
sqlalchemy_oso_cloud/session.py
sqlalchemy_oso_cloud-0.1.0.dist-info/LICENSE
sqlalchemy_oso_cloud-0.1.0.dist-info/METADATA
sqlalchemy_oso_cloud-0.1.0.dist-info/WHEEL
sqlalchemy_oso_cloud-0.1.0.dist-info/RECORD
