Metadata-Version: 2.3
Name: sqlalchemy-oso-cloud
Version: 0.1.0
Summary: First-class SQLAlchemy support for Oso Cloud
Author: Oso Security, Inc.
Requires-Python: >=3.9,<4
Classifier: Programming Language :: Python :: 3
Classifier: Programming Language :: Python :: 3.9
Classifier: Programming Language :: Python :: 3.10
Classifier: Programming Language :: Python :: 3.11
Classifier: Programming Language :: Python :: 3.12
Classifier: Programming Language :: Python :: 3.13
Requires-Dist: oso-cloud (>=2)
Requires-Dist: pyyaml (>=6.0.2,<7.0.0)
Requires-Dist: sqlalchemy (>=2)
